stopstart/__init__.py
stopstart/stopstart.py
tests/__init__.py
tests/test_stopstart.py
stopstart-0.7.0.dist-info/LICENSE
stopstart-0.7.0.dist-info/METADATA
stopstart-0.7.0.dist-info/WHEEL
stopstart-0.7.0.dist-info/top_level.txt
stopstart-0.7.0.dist-info/RECORD
