Metadata-Version: 2.1
Name: stopstart
Version: 0.7.0
Summary: A simple timer class for tracking elapsed time across multiple sessions, with detailed statistics and formatted output.
Home-page: https://github.com/ReverieTides/stopstart
Author: Dan
Author-email: break.a.wish@gmail.com
Requires-Python: >=3.8
License-File: LICENSE
Requires-Dist: setuptools >=75.3.0
